vfxdailies/__init__.py
vfxdailies/api.py
vfxdailies/daily.py
vfxdailies/environment.py
vfxdailies/factory.py
vfxdailies/nuke_write_config.py
vfxdailies/preset.py
vfxdailies/constant/__init__.py
vfxdailies/constant/engine.py
vfxdailies/constant/main.py
vfxdailies/constant/tracking.py
vfxdailies/constant/util.py
vfxdailies/engine/__init__.py
vfxdailies/engine/ffmpeg_engine.py
vfxdailies/engine/nuke_engine.py
vfxdailies/engine/nuke_template_engine.py
vfxdailies/engine/rvio_engine.py
vfxdailies/engine/video_engine.py
vfxdailies/tracking/__init__.py
vfxdailies/tracking/ftrack_tracking.py
vfxdailies/tracking/kitsu_tracking.py
vfxdailies/tracking/shotgun_tracking.py
vfxdailies/tracking/tracking.py
vfxdailies/ui/__init__.py
vfxdailies/ui/dcc.py
vfxdailies/ui/standalone.py
vfxdailies/ui/ui.py
vfxdailies-0.3.1.dist-info/licenses/LICENSE
vfxdailies-0.3.1.dist-info/METADATA
vfxdailies-0.3.1.dist-info/WHEEL
vfxdailies-0.3.1.dist-info/top_level.txt
vfxdailies-0.3.1.dist-info/RECORD
