Metadata-Version: 2.4
Name: vfxdailies
Version: 0.3.1
Summary: Tool for vfx/animation/film dailies production.
License: GPL-3.0-or-later
Project-URL: Homepage, https://github.com/vfxpaco85/vfxdailies
Requires-Python: >=3.8
License-File: LICENSE
Requires-Dist: PySide6==6.5.0
Requires-Dist: shotgun_api3==3.5.1
Provides-Extra: testing
Requires-Dist: pytest; extra == "testing"
Requires-Dist: pytest-cov; extra == "testing"
Requires-Dist: mock; extra == "testing"
Provides-Extra: lint
Requires-Dist: ruff; extra == "lint"
Dynamic: license-file
